nthuku_fast/__init__.py
nthuku_fast/core.py
nthuku_fast/kv_cache.py
nthuku_fast/optimized_moe.py
nthuku_fast/speculative_decoding.py
nthuku_fast/thinking_traces.py
nthuku_fast-0.1.2.dist-info/LICENSE
nthuku_fast-0.1.2.dist-info/METADATA
nthuku_fast-0.1.2.dist-info/WHEEL
nthuku_fast-0.1.2.dist-info/top_level.txt
nthuku_fast-0.1.2.dist-info/RECORD
