Metadata-Version: 2.1
Name: nthuku_fast
Version: 0.1.2
Summary: Nthuku-Fast: A blazing-fast multimodal AI model with vision and language understanding
Home-page: https://github.com/elijahnzeli1/Nthuku-fast_v2
Author: Nthuku Team
Author-email: 
License: MIT
Project-URL: Homepage, https://github.com/elijahnzeli1/Nthuku-fast_v2
Project-URL: Repository, https://github.com/elijahnzeli1/Nthuku-fast_v2
Project-URL: Bug Tracker, https://github.com/elijahnzeli1/Nthuku-fast_v2/issues
Keywords: machine learning,deep learning,transformers,multimodal,vision-language,mixture-of-experts
Classifier: Development Status :: 3 - Alpha
Classifier: Intended Audience :: Developers
Classifier: Intended Audience :: Science/Research
Classifier: License :: OSI Approved :: MIT License
Classifier: Programming Language :: Python :: 3
Classifier: Programming Language :: Python :: 3.8
Classifier: Programming Language :: Python :: 3.9
Classifier: Programming Language :: Python :: 3.10
Classifier: Programming Language :: Python :: 3.11
Classifier: Programming Language :: Python :: 3.12
Classifier: Topic :: Scientific/Engineering :: Artificial Intelligence
Requires-Python: >=3.8
License-File: LICENSE
Requires-Dist: torch >=2.0.0
Requires-Dist: transformers >=4.30.0
Requires-Dist: tqdm
Requires-Dist: Pillow
Requires-Dist: torchvision
Requires-Dist: numpy
Requires-Dist: safetensors
Requires-Dist: kagglehub
Requires-Dist: pandas
Requires-Dist: datasets
Provides-Extra: dev
Requires-Dist: pytest ; extra == 'dev'
Requires-Dist: black ; extra == 'dev'
Requires-Dist: flake8 ; extra == 'dev'
Requires-Dist: mypy ; extra == 'dev'
